pylint_pytest/__init__.py
pylint_pytest/utils.py
pylint_pytest/checkers/__init__.py
pylint_pytest/checkers/class_attr_loader.py
pylint_pytest/checkers/fixture.py
pylint_pytest/checkers/types.py
pylint_pytest-1.1.8.dist-info/LICENSE
pylint_pytest-1.1.8.dist-info/METADATA
pylint_pytest-1.1.8.dist-info/WHEEL
pylint_pytest-1.1.8.dist-info/top_level.txt
pylint_pytest-1.1.8.dist-info/RECORD
