Metadata-Version: 2.1
Name: pylint-pytest
Version: 1.1.8
Summary: A Pylint plugin to suppress pytest-related false positives.
Home-page: https://github.com/pylint-dev/pylint-pytest
Author: Stavros Ntentos
Author-email: 133706+stdedos@users.noreply.github.com
License: MIT
Project-URL: Changelog, https://github.com/pylint-dev/pylint-pytest/blob/master/CHANGELOG.md
Project-URL: Documentation, https://github.com/pylint-dev/pylint-pytest#readme
Project-URL: Say Thanks!, https://saythanks.io/to/stdedos
Project-URL: Source, https://github.com/pylint-dev/pylint-pytest
Project-URL: Tracker, https://github.com/pylint-dev/pylint-pytest/issues
Keywords: pylint,pytest,plugin
Classifier: Development Status :: 5 - Production/Stable
Classifier: Intended Audience :: Developers
Classifier: Topic :: Software Development :: Testing
Classifier: Topic :: Software Development :: Quality Assurance
Classifier: Programming Language :: Python
Classifier: Programming Language :: Python :: 3
Classifier: Programming Language :: Python :: 3.6
Classifier: Programming Language :: Python :: 3.7
Classifier: Programming Language :: Python :: 3.8
Classifier: Programming Language :: Python :: 3.9
Classifier: Programming Language :: Python :: 3.10
Classifier: Programming Language :: Python :: 3.11
Classifier: Programming Language :: Python :: Implementation :: CPython
Classifier: Operating System :: OS Independent
Classifier: License :: OSI Approved :: MIT License
Requires-Python: >=3.6
License-File: LICENSE
Requires-Dist: pylint>=2
Requires-Dist: pytest<=8.2.0,>=4.6
